main.py
rpi_servo_pwm/HardwarePWM.py
rpi_servo_pwm/__init__.py
rpi_servo_pwm-1.0.0.dist-info/licenses/LICENSE
rpi_servo_pwm-1.0.0.dist-info/METADATA
rpi_servo_pwm-1.0.0.dist-info/WHEEL
rpi_servo_pwm-1.0.0.dist-info/top_level.txt
rpi_servo_pwm-1.0.0.dist-info/RECORD
