Metadata-Version: 2.4
Name: rpi-servo-pwm
Version: 1.0.0
Summary: A lightweight library for controlling RC servos on the Raspberry Pi Zero 2 W using hardware PWM via the Linux kernel.
Author-email: "Chris L." <stylesuxx@gmail.com>
License: MIT License
Project-URL: Homepage, https://github.com/stylesuxx/rpi-servo-pwm
Project-URL: Issues, https://github.com/stylesuxx/rpi-servo-pwm/issues
Classifier: Programming Language :: Python :: 3
Classifier: Operating System :: OS Independent
Requires-Python: >=3.8
License-File: LICENSE
Dynamic: license-file
